gendev_tools/__init__.py
gendev_tools/gendev_err.py
gendev_tools/gendev_interface.py
gendev_tools/gendev_logger.py
gendev_tools/nat_mch/__init__.py
gendev_tools/nat_mch/nat_mch.py
gendev_tools/nat_mch/nat_mch_moxa.py
gendev_tools/nat_mch/nat_mch_telnet.py
gendev_tools/nat_mch/nat_mch_web.py
gendev_tools-1.1.dist-info/LICENSE
gendev_tools-1.1.dist-info/METADATA
gendev_tools-1.1.dist-info/WHEEL
gendev_tools-1.1.dist-info/top_level.txt
gendev_tools-1.1.dist-info/RECORD
