Metadata-Version: 2.1
Name: gendev-tools
Version: 1.1
Summary: Tools for managing the access to mTCA devices
Home-page: https://gitlab.esss.lu.se/hwcore/mtca/ess-gendev-tools
Author: Felipe Torres González
Author-email: felipe.torresgonzalez@ess.eu
License: UNKNOWN
Platform: UNKNOWN
Classifier: Programming Language :: Python :: 3
Classifier: License :: OSI Approved :: GNU General Public License v3 (GPLv3)
Classifier: Operating System :: POSIX :: Linux
Classifier: Development Status :: 4 - Beta
License-File: LICENSE
Requires-Dist: requests (>=2.22.0)
Requires-Dist: sphinx (>=3.5.4)
Requires-Dist: bs4 (>=0.0.1)
Requires-Dist: lxml (>=4.6.3)
Requires-Dist: html5lib (>=1.1)
